matheUI_backend/__init__.py
matheUI_backend/abstractGame.py
matheUI_backend/agentundercover.py
matheUI_backend/quiz.py
matheUI_backend/scharade.py
matheUI_backend/souqgame.py
matheUI_backend/souqgame_character.py
matheUI_backend/souqgame_level.py
matheUI_backend/config/__init__.py
matheUI_backend/data/__init__.py
matheUI_backend/data/AgentUndercover/__init__.py
matheUI_backend/data/Checkpoints/__init__.py
matheUI_backend/data/Quiz/__init__.py
matheUI_backend/data/Scharade/__init__.py
matheUI_backend/data/SouqGame/__init__.py
matheUI_backend-0.1.3.dist-info/LICENSE
matheUI_backend-0.1.3.dist-info/METADATA
matheUI_backend-0.1.3.dist-info/WHEEL
matheUI_backend-0.1.3.dist-info/top_level.txt
matheUI_backend-0.1.3.dist-info/RECORD
