Metadata-Version: 2.1
Name: matheUI-backend
Version: 0.1.3
Summary: little funny games package created by Samuel Brinkmann
Author: Samuel Brinkmann
License: MIT
License-File: LICENSE
Requires-Dist: pandas
Requires-Dist: numpy
Requires-Dist: tqdm
Provides-Extra: test
Requires-Dist: pytest ; extra == 'test'
Requires-Dist: pylint (!=2.5.0) ; extra == 'test'
Requires-Dist: isort ; extra == 'test'
